goldilocks/__init__.py
goldilocks/cmd.py
goldilocks/goldilocks.py
goldilocks/strategies.py
goldilocks/util.py
goldilocks-0.1.1.dist-info/DESCRIPTION.rst
goldilocks-0.1.1.dist-info/METADATA
goldilocks-0.1.1.dist-info/RECORD
goldilocks-0.1.1.dist-info/WHEEL
goldilocks-0.1.1.dist-info/entry_points.txt
goldilocks-0.1.1.dist-info/metadata.json
goldilocks-0.1.1.dist-info/top_level.txt
