Metadata-Version: 2.0
Name: goldilocks
Version: 0.1.1
Summary: Locating genomic regions that are "just right".
Home-page: https://github.com/samstudio8/goldilocks
Author: Sam Nicholls
Author-email: sam@samnicholls.net
License: UNKNOWN
Platform: UNKNOWN
Classifier: Development Status :: 2 - Pre-Alpha
Classifier: Intended Audience :: Developers
Classifier: Intended Audience :: Science/Research
Classifier: Programming Language :: Python :: 2
Classifier: Programming Language :: Python :: 2.7
Classifier: Topic :: Scientific/Engineering
Classifier: Topic :: Scientific/Engineering :: Bio-Informatics
Classifier: License :: OSI Approved :: MIT License
Requires-Dist: matplotlib
Requires-Dist: numpy
